Metadata-Version: 2.1
Name: pycom-ota-server
Version: 0.0.3
Summary: Pycom OTA firmware server
Home-page: https://github.com/snebot-bg/pycom-ota-server
Author: snebot
Author-email: snebot@bitgrup.com
License: UNKNOWN
Platform: UNKNOWN
